benediction/__init__.py
benediction/_utils/solver.py
benediction/_utils/text.py
benediction/app.py
benediction/errors.py
benediction/layout.py
benediction/screen.py
benediction/style/__init__.py
benediction/style/color/.gitignore
benediction/style/color/__init__.py
benediction/style/color/_color.py
benediction/style/color/tailwind.py
benediction/style/color/x11.py
benediction/style/style.py
benediction/window.py
benediction-0.1.0.dist-info/LICENSE
benediction-0.1.0.dist-info/WHEEL
benediction-0.1.0.dist-info/METADATA
benediction-0.1.0.dist-info/RECORD
