Metadata-Version: 2.1
Name: benediction
Version: 0.1.0
Summary: 
Author: austerj
Requires-Python: >=3.12,<4.0
Classifier: Programming Language :: Python :: 3
Requires-Dist: windows-curses (>=2.3.2,<3.0.0); sys_platform == "windows"
